grammar_zoo/__init__.py
grammar_zoo/main.py
grammar_zoo/resources/__init__.py
grammar_zoo/resources/cola_in_domain_dev.tsv
grammar_zoo-0.1.1.dist-info/LICENSE
grammar_zoo-0.1.1.dist-info/METADATA
grammar_zoo-0.1.1.dist-info/WHEEL
grammar_zoo-0.1.1.dist-info/entry_points.txt
grammar_zoo-0.1.1.dist-info/RECORD
